{
  "$schema": "https://schemas.wp.org/trunk/block.json",
  "apiVersion": 3,
  "name": "hhc-blocks/business-info",
  "version": "0.1.0",
  "title": "Business Info",
  "category": "text",
  "icon": "store",
  "description": "Custom block for the ACF Pro Options Page.",
  "example": {},
  "supports": {
    "align": false,
    "html": false
  },
  "textdomain": "business-info",
  "editorScript": "file:./index.js",
  "editorStyle": "file:./index.css",
  "render": "file:./render.php",
  "style": "file:./style-index.css",
  "viewScript": "file:./view.js"
}